[
    {
        "id": "71581b6ee8b7bff4",
        "type": "modbustcp-read",
        "z": "ea112dba29e7ca33",
        "name": "",
        "topic": "",
        "dataType": "HoldingRegister",
        "adr": "4",
        "quantity": "2",
        "rate": "1",
        "rateUnit": "s",
        "server": "b75d2c41bd5aacdb",
        "ieeeType": "off",
        "ieeeBE": "true",
        "x": 210,
        "y": 300,
        "wires": [
            [
                "7190f2d7beb3ec8a"
            ]
        ]
    },
    {
        "id": "51b536b01385dc4f",
        "type": "change",
        "z": "ea112dba29e7ca33",
        "name": "",
        "rules": [
            {
                "t": "set",
                "p": "tag1",
                "pt": "global",
                "to": "payload",
                "tot": "msg"
            }
        ],
        "action": "",
        "property": "",
        "from": "",
        "to": "",
        "reg": false,
        "x": 860,
        "y": 320,
        "wires": [
            []
        ]
    },
    {
        "id": "6568b2868dce34e6",
        "type": "tofloat",
        "z": "ea112dba29e7ca33",
        "name": "",
        "x": 610,
        "y": 300,
        "wires": [
            [
                "15d08526b14b79e7",
                "51b536b01385dc4f"
            ]
        ]
    },
    {
        "id": "3c3ea947872309ca",
        "type": "inject",
        "z": "ea112dba29e7ca33",
        "name": "",
        "props": [
            {
                "p": "payload"
            },
            {
                "p": "topic",
                "vt": "str"
            }
        ],
        "repeat": "",
        "crontab": "",
        "once": false,
        "onceDelay": 0.1,
        "topic": "",
        "payload": "41a00100",
        "payloadType": "str",
        "x": 420,
        "y": 140,
        "wires": [
            [
                "732f9b2acaa53d79"
            ]
        ]
    },
    {
        "id": "15d08526b14b79e7",
        "type": "debug",
        "z": "ea112dba29e7ca33",
        "name": "debug 4",
        "active": true,
        "tosidebar": true,
        "console": false,
        "tostatus": false,
        "complete": "false",
        "statusVal": "",
        "statusType": "auto",
        "x": 840,
        "y": 260,
        "wires": []
    },
    {
        "id": "7190f2d7beb3ec8a",
        "type": "function",
        "z": "ea112dba29e7ca33",
        "name": "function 1",
        "func": "// Convert each decimal value to 2-digit uppercase hex\nlet hex0 = Number(msg.payload[0]).toString(16).toUpperCase().padStart(4, '0');\nlet hex1 = Number(msg.payload[1]).toString(16).toUpperCase().padStart(4, '0');\n// Combine them into one string\nmsg.payload = hex0 + hex1;\n\nreturn msg;",
        "outputs": 1,
        "timeout": 0,
        "noerr": 0,
        "initialize": "",
        "finalize": "",
        "libs": [],
        "x": 400,
        "y": 300,
        "wires": [
            [
                "6568b2868dce34e6"
            ]
        ]
    },
    {
        "id": "732f9b2acaa53d79",
        "type": "tofloat",
        "z": "ea112dba29e7ca33",
        "name": "",
        "x": 570,
        "y": 140,
        "wires": [
            [
                "4ed61d7ed0c10ccb"
            ]
        ]
    },
    {
        "id": "4ed61d7ed0c10ccb",
        "type": "debug",
        "z": "ea112dba29e7ca33",
        "name": "debug 5",
        "active": true,
        "tosidebar": true,
        "console": false,
        "tostatus": false,
        "complete": "false",
        "statusVal": "",
        "statusType": "auto",
        "x": 740,
        "y": 140,
        "wires": []
    },
    {
        "id": "b75d2c41bd5aacdb",
        "type": "modbustcp-server",
        "name": "local",
        "host": "127.0.0.1",
        "port": "1502",
        "unit_id": 1,
        "reconnecttimeout": "3"
    },
    {
        "id": "7e971527b2efdae7",
        "type": "global-config",
        "env": [],
        "modules": {
            "node-red-contrib-modbustcp": "1.2.3",
            "node-red-contrib-tofloat": "1.0.0"
        }
    }
]